{
  "20250926152012-Saibai-FLOOD-GUI": {
    "template_version": "0.2-desktop",
    "hazard": "FLOOD",
    "incident_id": "20250926152012-Saibai-FLOOD-GUI",
    "severity": "Warning",
    "area": "Saibai Island low-lying areas",
    "effective_from": "2025-09-26T15:19",
    "expected_until": "2025-09-26T15:19",
    "msg": {
      "en": "",
      "kkya": ""
    },
    "sections": {
      "issued": {
        "en": "a",
        "kkya": "a"
      },
      "next_update": {
        "en": "a",
        "kkya": "a"
      },
      "expecting": {
        "en": "a",
        "kkya": "a"
      },
      "actions": {
        "en": "a",
        "kkya": "a"
      },
      "support": {
        "en": "a",
        "kkya": "a"
      },
      "more_info": {
        "en": "a",
        "kkya": "a"
      }
    },
    "channels_hint": [
      "sms",
      "email",
      "voice",
      "meshtastic"
    ],
    "auto_fill": {
      "issuer": "Saibai Disaster Management",
      "contact": "07 0000 0000"
    }
  },
  "20250926152103-Saibai-FLOOD-GUI": {
    "template_version": "0.2-desktop",
    "hazard": "FLOOD",
    "incident_id": "20250926152103-Saibai-FLOOD-GUI",
    "severity": "Warning",
    "area": "Saibai Island low-lying areas",
    "effective_from": "2025-09-26T15:19",
    "expected_until": "2025-09-26T15:19",
    "msg": {
      "en": "",
      "kkya": ""
    },
    "sections": {
      "issued": {
        "en": "a",
        "kkya": "a"
      },
      "next_update": {
        "en": "a",
        "kkya": "a"
      },
      "expecting": {
        "en": "a",
        "kkya": "a"
      },
      "actions": {
        "en": "a",
        "kkya": "a"
      },
      "support": {
        "en": "a",
        "kkya": "a"
      },
      "more_info": {
        "en": "a",
        "kkya": "a"
      }
    },
    "channels_hint": [
      "sms",
      "email",
      "voice",
      "meshtastic"
    ],
    "auto_fill": {
      "issuer": "Saibai Disaster Management",
      "contact": "07 0000 0000"
    }
  },
  "20250926152141-Saibai-FLOOD-GUI": {
    "template_version": "0.2-desktop",
    "hazard": "FLOOD",
    "incident_id": "20250926152141-Saibai-FLOOD-GUI",
    "severity": "Warning",
    "area": "Saibai Island low-lying areas",
    "effective_from": "2025-09-26T15:19",
    "expected_until": "2025-09-26T15:19",
    "msg": {
      "en": "",
      "kkya": ""
    },
    "sections": {
      "issued": {
        "en": "a",
        "kkya": "a"
      },
      "next_update": {
        "en": "a",
        "kkya": "a"
      },
      "expecting": {
        "en": "a",
        "kkya": "a"
      },
      "actions": {
        "en": "a",
        "kkya": "a"
      },
      "support": {
        "en": "a",
        "kkya": "a"
      },
      "more_info": {
        "en": "a",
        "kkya": "a"
      }
    },
    "channels_hint": [
      "sms",
      "email",
      "voice",
      "meshtastic"
    ],
    "auto_fill": {
      "issuer": "Saibai Disaster Management",
      "contact": "07 0000 0000"
    }
  },
  "20250926152340-Saibai-FLOOD-GUI": {
    "template_version": "0.2-desktop",
    "hazard": "FLOOD",
    "incident_id": "20250926152340-Saibai-FLOOD-GUI",
    "severity": "Warning",
    "area": "Saibai Island low-lying areas",
    "effective_from": "2025-09-26T15:19",
    "expected_until": "2025-09-26T15:19",
    "msg": {
      "en": "",
      "kkya": ""
    },
    "sections": {
      "issued": {
        "en": "a",
        "kkya": "a"
      },
      "next_update": {
        "en": "a",
        "kkya": "a"
      },
      "expecting": {
        "en": "a",
        "kkya": "a"
      },
      "actions": {
        "en": "a",
        "kkya": "a"
      },
      "support": {
        "en": "a",
        "kkya": "a"
      },
      "more_info": {
        "en": "a",
        "kkya": "a"
      }
    },
    "channels_hint": [
      "sms",
      "email",
      "voice",
      "meshtastic"
    ],
    "auto_fill": {
      "issuer": "Saibai Disaster Management",
      "contact": "07 0000 0000"
    }
  },
  "20250926152443-Saibai-FLOOD-GUI": {
    "template_version": "0.2-desktop",
    "hazard": "FLOOD",
    "incident_id": "20250926152443-Saibai-FLOOD-GUI",
    "severity": "Warning",
    "area": "Saibai Island low-lying areas",
    "effective_from": "2025-09-26T15:24",
    "expected_until": "2025-09-26T15:24",
    "msg": {
      "en": "",
      "kkya": ""
    },
    "sections": {
      "issued": {
        "en": "a",
        "kkya": "a"
      },
      "next_update": {
        "en": "a",
        "kkya": "a"
      },
      "expecting": {
        "en": "a",
        "kkya": "a"
      },
      "actions": {
        "en": "a",
        "kkya": "a"
      },
      "support": {
        "en": "a",
        "kkya": "a"
      },
      "more_info": {
        "en": "a",
        "kkya": "a"
      }
    },
    "channels_hint": [
      "sms",
      "email",
      "voice",
      "meshtastic"
    ],
    "auto_fill": {
      "issuer": "Saibai Disaster Management",
      "contact": "07 0000 0000"
    }
  },
  "20250926152927-Saibai-FLOOD-GUI": {
    "template_version": "0.2-desktop",
    "hazard": "FLOOD",
    "incident_id": "20250926152927-Saibai-FLOOD-GUI",
    "severity": "Warning",
    "area": "Saibai Island low-lying areas",
    "effective_from": "2025-09-26T15:29",
    "expected_until": "2025-09-26T15:29",
    "msg": {
      "en": "",
      "kkya": ""
    },
    "sections": {
      "issued": {
        "en": "a",
        "kkya": "a"
      },
      "next_update": {
        "en": "a",
        "kkya": "a"
      },
      "expecting": {
        "en": "a",
        "kkya": "a"
      },
      "actions": {
        "en": "a",
        "kkya": "a"
      },
      "support": {
        "en": "a",
        "kkya": "a"
      },
      "more_info": {
        "en": "a",
        "kkya": "a"
      }
    },
    "channels_hint": [
      "sms",
      "email",
      "voice",
      "meshtastic"
    ],
    "auto_fill": {
      "issuer": "Saibai Disaster Management",
      "contact": "07 0000 0000"
    }
  },
  "20250926153535-Saibai-FLOOD-GUI": {
    "template_version": "0.2-desktop",
    "hazard": "FLOOD",
    "incident_id": "20250926153535-Saibai-FLOOD-GUI",
    "severity": "Warning",
    "area": "Saibai Island low-lying areas",
    "effective_from": "2025-09-26T15:35",
    "expected_until": "2025-09-26T15:35",
    "msg": {
      "en": "",
      "kkya": ""
    },
    "sections": {
      "issued": {
        "en": "a",
        "kkya": "a"
      },
      "next_update": {
        "en": "a",
        "kkya": "a"
      },
      "expecting": {
        "en": "a",
        "kkya": "a"
      },
      "actions": {
        "en": "a",
        "kkya": "a"
      },
      "support": {
        "en": "a",
        "kkya": "a"
      },
      "more_info": {
        "en": "a",
        "kkya": "a"
      }
    },
    "channels_hint": [
      "sms",
      "email",
      "voice",
      "meshtastic"
    ],
    "auto_fill": {
      "issuer": "Saibai Disaster Management",
      "contact": "07 0000 0000"
    }
  },
  "20250926154021-Saibai-FLOOD-GUI": {
    "template_version": "0.2-desktop",
    "hazard": "FLOOD",
    "incident_id": "20250926154021-Saibai-FLOOD-GUI",
    "severity": "Warning",
    "area": "Saibai Island low-lying areas",
    "effective_from": "2025-09-26T15:40",
    "expected_until": "2025-09-26T15:40",
    "msg": {
      "en": "",
      "kkya": ""
    },
    "sections": {
      "issued": {
        "en": "a",
        "kkya": "a"
      },
      "next_update": {
        "en": "a",
        "kkya": "a"
      },
      "expecting": {
        "en": "a",
        "kkya": "a"
      },
      "actions": {
        "en": "a",
        "kkya": "a"
      },
      "support": {
        "en": "a",
        "kkya": "a"
      },
      "more_info": {
        "en": "a",
        "kkya": "a"
      }
    },
    "channels_hint": [
      "sms",
      "email",
      "voice",
      "meshtastic"
    ],
    "auto_fill": {
      "issuer": "Saibai Disaster Management",
      "contact": "07 0000 0000"
    }
  },
  "20250926154437-Saibai-FLOOD-GUI": {
    "template_version": "0.2-desktop",
    "hazard": "FLOOD",
    "incident_id": "20250926154437-Saibai-FLOOD-GUI",
    "severity": "Warning",
    "area": "Saibai Island low-lying areas",
    "effective_from": "2025-09-26T15:44",
    "expected_until": "2025-09-26T15:44",
    "msg": {
      "en": "",
      "kkya": ""
    },
    "sections": {
      "issued": {
        "en": "a",
        "kkya": "a"
      },
      "next_update": {
        "en": "a",
        "kkya": "a"
      },
      "expecting": {
        "en": "a",
        "kkya": "a"
      },
      "actions": {
        "en": "a",
        "kkya": "a"
      },
      "support": {
        "en": "a",
        "kkya": "a"
      },
      "more_info": {
        "en": "a",
        "kkya": "a"
      }
    },
    "channels_hint": [
      "sms",
      "email",
      "voice",
      "meshtastic"
    ],
    "auto_fill": {
      "issuer": "Saibai Disaster Management",
      "contact": "07 0000 0000"
    }
  },
  "20250926154806-Saibai-FLOOD-GUI": {
    "template_version": "0.2-desktop",
    "hazard": "FLOOD",
    "incident_id": "20250926154806-Saibai-FLOOD-GUI",
    "severity": "Warning",
    "area": "Saibai Island low-lying areas",
    "effective_from": "2025-09-26T15:48",
    "expected_until": "2025-09-26T15:48",
    "msg": {
      "en": "",
      "kkya": ""
    },
    "sections": {
      "issued": {
        "en": "a",
        "kkya": "a"
      },
      "next_update": {
        "en": "a",
        "kkya": "a"
      },
      "expecting": {
        "en": "a",
        "kkya": "a"
      },
      "actions": {
        "en": "a",
        "kkya": "a"
      },
      "support": {
        "en": "a",
        "kkya": "a"
      },
      "more_info": {
        "en": "a",
        "kkya": "a"
      }
    },
    "channels_hint": [
      "sms",
      "email",
      "voice",
      "meshtastic"
    ],
    "auto_fill": {
      "issuer": "Saibai Disaster Management",
      "contact": "07 0000 0000"
    }
  },
  "20250926154849-Saibai-FLOOD-GUI": {
    "template_version": "0.2-desktop",
    "hazard": "FLOOD",
    "incident_id": "20250926154849-Saibai-FLOOD-GUI",
    "severity": "Warning",
    "area": "Saibai Island low-lying areas",
    "effective_from": "2025-09-26T15:48",
    "expected_until": "2025-09-26T15:48",
    "msg": {
      "en": "",
      "kkya": ""
    },
    "sections": {
      "issued": {
        "en": "a",
        "kkya": "a"
      },
      "next_update": {
        "en": "a",
        "kkya": "a"
      },
      "expecting": {
        "en": "a",
        "kkya": "a"
      },
      "actions": {
        "en": "a",
        "kkya": "a"
      },
      "support": {
        "en": "a",
        "kkya": "a"
      },
      "more_info": {
        "en": "a",
        "kkya": "a"
      }
    },
    "channels_hint": [
      "sms",
      "email",
      "voice",
      "meshtastic"
    ],
    "auto_fill": {
      "issuer": "Saibai Disaster Management",
      "contact": "07 0000 0000"
    }
  }
}